hoes/__init__.py
hoes/test.py
hoes-0.0.3.dist-info/METADATA
hoes-0.0.3.dist-info/WHEEL
hoes-0.0.3.dist-info/top_level.txt
hoes-0.0.3.dist-info/RECORD
